odoo/addons/fleet_vehicle_fuel_type_ethanol/README.rst
odoo/addons/fleet_vehicle_fuel_type_ethanol/__init__.py
odoo/addons/fleet_vehicle_fuel_type_ethanol/__manifest__.py
odoo/addons/fleet_vehicle_fuel_type_ethanol/i18n/es.po
odoo/addons/fleet_vehicle_fuel_type_ethanol/i18n/fleet_vehicle_fuel_type_ethanol.pot
odoo/addons/fleet_vehicle_fuel_type_ethanol/i18n/it.po
odoo/addons/fleet_vehicle_fuel_type_ethanol/i18n/pt_BR.po
odoo/addons/fleet_vehicle_fuel_type_ethanol/i18n/sv.po
odoo/addons/fleet_vehicle_fuel_type_ethanol/models/__init__.py
odoo/addons/fleet_vehicle_fuel_type_ethanol/models/fleet_vehicle.py
odoo/addons/fleet_vehicle_fuel_type_ethanol/readme/CONTRIBUTORS.md
odoo/addons/fleet_vehicle_fuel_type_ethanol/readme/CREDITS.md
odoo/addons/fleet_vehicle_fuel_type_ethanol/readme/DESCRIPTION.md
odoo/addons/fleet_vehicle_fuel_type_ethanol/static/description/banner.png
odoo/addons/fleet_vehicle_fuel_type_ethanol/static/description/icon.png
odoo/addons/fleet_vehicle_fuel_type_ethanol/static/description/index.html
odoo_addon_fleet_vehicle_fuel_type_ethanol-18.0.1.0.0.2.dist-info/METADATA
odoo_addon_fleet_vehicle_fuel_type_ethanol-18.0.1.0.0.2.dist-info/WHEEL
odoo_addon_fleet_vehicle_fuel_type_ethanol-18.0.1.0.0.2.dist-info/top_level.txt
odoo_addon_fleet_vehicle_fuel_type_ethanol-18.0.1.0.0.2.dist-info/RECORD
